psgup/__init__.py
psgup/__main__.py
psgup/psgup.py
psgup-2.4.dist-info/METADATA
psgup-2.4.dist-info/WHEEL
psgup-2.4.dist-info/entry_points.txt
psgup-2.4.dist-info/top_level.txt
psgup-2.4.dist-info/RECORD
