Metadata-Version: 2.1
Name: psgup
Version: 2.4
Summary: Application distribution via PyPI
Home-page: https://github.com/PySimpleGUI
Author: PySimpleSoft
Author-email: someone@somewhere.com
License: Free To Use But Restricted
Keywords: PySimpleGUI Application Distribution
Platform: UNKNOWN
Classifier: Development Status :: 5 - Production/Stable
Classifier: Intended Audience :: Developers
Classifier: License :: Free To Use But Restricted
Classifier: Operating System :: OS Independent
Classifier: Programming Language :: Python :: 3
Classifier: Programming Language :: Python :: 3.6
Classifier: Programming Language :: Python :: 3.7
Classifier: Programming Language :: Python :: 3.8
Classifier: Programming Language :: Python :: 3.9
Classifier: Programming Language :: Python :: 3.10
Classifier: Programming Language :: Python :: 3.11
Classifier: Programming Language :: Python :: 3.12
Classifier: Programming Language :: Python :: 3.13
Classifier: Topic :: Multimedia :: Graphics
Classifier: Topic :: Software Development :: User Interfaces
Classifier: Development Status :: 2 - Pre-Alpha
Classifier: Development Status :: 3 - Alpha
Requires-Python: >=3.6
Requires-Dist: PySimpleGUI
